fluent/__init__.py
fluent/syntax/__init__.py
fluent/syntax/ast.py
fluent/syntax/errors.py
fluent/syntax/parser.py
fluent/syntax/serializer.py
fluent/syntax/stream.py
fluent/syntax/visitor.py
fluent.syntax-0.18.0.dist-info/METADATA
fluent.syntax-0.18.0.dist-info/WHEEL
fluent.syntax-0.18.0.dist-info/top_level.txt
fluent.syntax-0.18.0.dist-info/RECORD
