Metadata-Version: 2.1
Name: fluent.syntax
Version: 0.18.0
Summary: Localization library for expressive translations.
Home-page: https://github.com/projectfluent/python-fluent
Author: Mozilla
Author-email: l10n-drivers@mozilla.org
License: APL 2
Keywords: fluent,localization,l10n
Platform: UNKNOWN
Classifier: Development Status :: 3 - Alpha
Classifier: Intended Audience :: Developers
Classifier: License :: OSI Approved :: Apache Software License
Classifier: Programming Language :: Python :: 2.7
Classifier: Programming Language :: Python :: 3.5
